README.md
setup.py
vmnet/__init__.py
vmnet.egg-info/PKG-INFO
vmnet.egg-info/SOURCES.txt
vmnet.egg-info/dependency_links.txt
vmnet.egg-info/top_level.txt